tgraphx/__init__.py
tgraphx-0.0.1.dist-info/METADATA
tgraphx-0.0.1.dist-info/WHEEL
tgraphx-0.0.1.dist-info/top_level.txt
tgraphx-0.0.1.dist-info/RECORD
