Metadata-Version: 2.4
Name: tgraphx
Version: 0.0.1
Summary: Early placeholder for TGraphX PyPI reservation
Author: Arash Sajjadi
Author-email: Arash Sajjadi <arash.sajjadi@usask.ca>
License: MIT
Requires-Python: >=3.8
Dynamic: author
Dynamic: requires-python
